amap_mcp/__init__.py
amap_mcp/server.py
amap_mcp/amap/__init__.py
amap_mcp/amap/client.py
amap_mcp/amap/query_weather/__init__.py
amap_mcp/amap/query_weather/client.py
amap_mcp-0.0.4.dist-info/METADATA
amap_mcp-0.0.4.dist-info/WHEEL
amap_mcp-0.0.4.dist-info/entry_points.txt
amap_mcp-0.0.4.dist-info/licenses/LICENSE
amap_mcp-0.0.4.dist-info/RECORD
