Metadata-Version: 2.4
Name: amap-mcp
Version: 0.0.4
Summary: AMap MCP Server
License: MIT License
License-File: LICENSE
Keywords: amap,mcp,query-weather
Requires-Python: >=3.10
Requires-Dist: fastapi==0.109.2
Requires-Dist: httpx>=0.28.1
Requires-Dist: mcp[cli]>=1.6.0
Requires-Dist: pydantic>=2.6.1
Requires-Dist: pytest>=8.0.0
Requires-Dist: python-dotenv==1.0.1
Requires-Dist: requests>=2.31.0
Requires-Dist: uvicorn==0.27.1
Provides-Extra: dev
Requires-Dist: build>=1.0.3; extra == 'dev'
Requires-Dist: fastmcp==0.4.1; extra == 'dev'
Requires-Dist: pre-commit==3.6.2; extra == 'dev'
Requires-Dist: pytest-cov==4.1.0; extra == 'dev'
Requires-Dist: pytest==8.0.0; extra == 'dev'
Requires-Dist: ruff==0.3.0; extra == 'dev'
Requires-Dist: twine==6.1.0; extra == 'dev'
